{
  "type": "FeatureCollection",
  "metadata": {
    "generated": 1746844164000,
    "url": "https://earthquake.usgs.gov/earthquakes/feed/v1.0/summary/all_hour.geojson",
    "title": "USGS All Earthquakes, Past Hour",
    "status": 200,
    "api": "1.14.1",
    "count": 11
  },
  "features": [
    {
      "type": "Feature",
      "properties": {
        "mag": 0.77,
        "place": "7 km NNW of The Geysers, CA",
        "time": 1746843909740,
        "updated": 1746844008914,
        "url": "https://earthquake.usgs.gov/earthquakes/eventpage/nc75179161",
        "detail": "https://earthquake.usgs.gov/earthquakes/feed/v1.0/detail/nc75179161.geojson",
        "title": "M 0.8 - 7 km NNW of The Geysers, CA"
      },
      "geometry": {
        "type": "Point",
        "coordinates": [
          -122.813835144043,
          38.8245010375977,
          2.1800000667572
        ]
      }
    },
    {
      "type": "Feature",
      "properties": {
        "mag": 1.3,
        "place": "28 km SW of Hope, Alaska",
        "time": 1746843809321,
        "updated": 1746843942937,
        "url": "https://earthquake.usgs.gov/earthquakes/eventpage/ak0255z16z50",
        "detail": "https://earthquake.usgs.gov/earthquakes/feed/v1.0/detail/ak0255z16z50.geojson",
        "title": "M 1.3 - 28 km SW of Hope, Alaska"
      },
      "geometry": {
        "type": "Point",
        "coordinates": [
          -150.0661,
          60.7712,
          34.9
        ]
      }
    },
    {
      "type": "Feature",
      "properties": {
        "mag": 1.04,
        "place": "5 km WNW of Cobb, CA",
        "time": 1746843171780,
        "updated": 1746843267943,
        "url": "https://earthquake.usgs.gov/earthquakes/eventpage/nc75179156",
        "detail": "https://earthquake.usgs.gov/earthquakes/feed/v1.0/detail/nc75179156.geojson",
        "title": "M 1.0 - 5 km WNW of Cobb, CA"
      },
      "geometry": {
        "type": "Point",
        "coordinates": [
          -122.781997680664,
          38.8366661071777,
          1.79999995231628
        ]
      }
    },
    {
      "type": "Feature",
      "properties": {
        "mag": 2.19,
        "place": "3 km NE of Rincón, Puerto Rico",
        "time": 1746842836910,
        "updated": 1746843501160,
        "url": "https://earthquake.usgs.gov/earthquakes/eventpage/pr71481813",
        "detail": "https://earthquake.usgs.gov/earthquakes/feed/v1.0/detail/pr71481813.geojson",
        "title": "M 2.2 - 3 km NE of Rincón, Puerto Rico"
      },
      "geometry": {
        "type": "Point",
        "coordinates": [
          -67.2246666666667,
          18.365,
          21.05
        ]
      }
    },
    {
      "type": "Feature",
      "properties": {
        "mag": 1.38,
        "place": "24 km ESE of Little Lake, CA",
        "time": 1746842214620,
        "updated": 1746842418453,
        "url": "https://earthquake.usgs.gov/earthquakes/eventpage/ci41149744",
        "detail": "https://earthquake.usgs.gov/earthquakes/feed/v1.0/detail/ci41149744.geojson",
        "title": "M 1.4 - 24 km ESE of Little Lake, CA"
      },
      "geometry": {
        "type": "Point",
        "coordinates": [
          -117.6485,
          35.8661667,
          5.71
        ]
      }
    },
    {
      "type": "Feature",
      "properties": {
        "mag": 1.03,
        "place": "4 km W of Cobb, CA",
        "time": 1746842154090,
        "updated": 1746844038737,
        "url": "https://earthquake.usgs.gov/earthquakes/eventpage/nc75179151",
        "detail": "https://earthquake.usgs.gov/earthquakes/feed/v1.0/detail/nc75179151.geojson",
        "title": "M 1.0 - 4 km W of Cobb, CA"
      },
      "geometry": {
        "type": "Point",
        "coordinates": [
          -122.764167785645,
          38.8178329467773,
          1.75999999046326
        ]
      }
    },
    {
      "type": "Feature",
      "properties": {
        "mag": 1.06,
        "place": "4 km W of Cobb, CA",
        "time": 1746842135660,
        "updated": 1746843440673,
        "url": "https://earthquake.usgs.gov/earthquakes/eventpage/nc75179146",
        "detail": "https://earthquake.usgs.gov/earthquakes/feed/v1.0/detail/nc75179146.geojson",
        "title": "M 1.1 - 4 km W of Cobb, CA"
      },
      "geometry": {
        "type": "Point",
        "coordinates": [
          -122.763496398926,
          38.8176651000977,
          1.4099999666214
        ]
      }
    },
    {
      "type": "Feature",
      "properties": {
        "mag": 1.1,
        "place": "57 km WNW of Stevens Village, Alaska",
        "time": 1746842037387,
        "updated": 1746842710350,
        "url": "https://earthquake.usgs.gov/earthquakes/eventpage/ak0255z0s16r",
        "detail": "https://earthquake.usgs.gov/earthquakes/feed/v1.0/detail/ak0255z0s16r.geojson",
        "title": "M 1.1 - 57 km WNW of Stevens Village, Alaska"
      },
      "geometry": {
        "type": "Point",
        "coordinates": [
          -150.2712,
          66.208,
          3.8
        ]
      }
    },
    {
      "type": "Feature",
      "properties": {
        "mag": 1.2,
        "place": "36 km ENE of Susitna North, Alaska",
        "time": 1746841831748,
        "updated": 1746841946620,
        "url": "https://earthquake.usgs.gov/earthquakes/eventpage/ak0255z0rc1y",
        "detail": "https://earthquake.usgs.gov/earthquakes/feed/v1.0/detail/ak0255z0rc1y.geojson",
        "title": "M 1.2 - 36 km ENE of Susitna North, Alaska"
      },
      "geometry": {
        "type": "Point",
        "coordinates": [
          -149.1683,
          62.2368,
          20.6
        ]
      }
    },
    {
      "type": "Feature",
      "properties": {
        "mag": 0.53,
        "place": "12 km SSE of Anza, CA",
        "time": 1746841595640,
        "updated": 1746841841085,
        "url": "https://earthquake.usgs.gov/earthquakes/eventpage/ci41149728",
        "detail": "https://earthquake.usgs.gov/earthquakes/feed/v1.0/detail/ci41149728.geojson",
        "title": "M 0.5 - 12 km SSE of Anza, CA"
      },
      "geometry": {
        "type": "Point",
        "coordinates": [
          -116.6413333,
          33.4483333,
          7.21
        ]
      }
    },
    {
      "type": "Feature",
      "properties": {
        "mag": 2,
        "place": "20 km W of Willow, Alaska",
        "time": 1746841356959,
        "updated": 1746841445425,
        "url": "https://earthquake.usgs.gov/earthquakes/eventpage/ak0255z0pmq7",
        "detail": "https://earthquake.usgs.gov/earthquakes/feed/v1.0/detail/ak0255z0pmq7.geojson",
        "title": "M 2.0 - 20 km W of Willow, Alaska"
      },
      "geometry": {
        "type": "Point",
        "coordinates": [
          -150.4335,
          61.74,
          46.4
        ]
      }
    }
  ]
}