{
  "type": "FeatureCollection",
  "metadata": {
    "generated": 1746716560000,
    "url": "https://earthquake.usgs.gov/earthquakes/feed/v1.0/summary/all_hour.geojson",
    "title": "USGS All Earthquakes, Past Hour",
    "status": 200,
    "api": "1.14.1",
    "count": 8
  },
  "features": [
    {
      "type": "Feature",
      "properties": {
        "mag": 1.62,
        "place": "8 km NNE of Coso Junction, CA",
        "time": 1746715823390,
        "updated": 1746716042821,
        "url": "https://earthquake.usgs.gov/earthquakes/eventpage/ci41147880",
        "detail": "https://earthquake.usgs.gov/earthquakes/feed/v1.0/detail/ci41147880.geojson",
        "title": "M 1.6 - 8 km NNE of Coso Junction, CA"
      },
      "geometry": {
        "type": "Point",
        "coordinates": [
          -117.9235,
          36.111,
          2.31
        ]
      }
    },
    {
      "type": "Feature",
      "properties": {
        "mag": 1.95,
        "place": "2 km ESE of Lake Henshaw, CA",
        "time": 1746715725930,
        "updated": 1746716360070,
        "url": "https://earthquake.usgs.gov/earthquakes/eventpage/ci41147872",
        "detail": "https://earthquake.usgs.gov/earthquakes/feed/v1.0/detail/ci41147872.geojson",
        "title": "M 2.0 - 2 km ESE of Lake Henshaw, CA"
      },
      "geometry": {
        "type": "Point",
        "coordinates": [
          -116.7431667,
          33.2311667,
          8.8
        ]
      }
    },
    {
      "type": "Feature",
      "properties": {
        "mag": 1.01,
        "place": "5 km WNW of Cobb, CA",
        "time": 1746715444150,
        "updated": 1746715542817,
        "url": "https://earthquake.usgs.gov/earthquakes/eventpage/nc75178476",
        "detail": "https://earthquake.usgs.gov/earthquakes/feed/v1.0/detail/nc75178476.geojson",
        "title": "M 1.0 - 5 km WNW of Cobb, CA"
      },
      "geometry": {
        "type": "Point",
        "coordinates": [
          -122.782669067383,
          38.8375015258789,
          1.94000005722046
        ]
      }
    },
    {
      "type": "Feature",
      "properties": {
        "mag": 2.61,
        "place": "10 km WNW of Corona, CA",
        "time": 1746715394180,
        "updated": 1746716261269,
        "url": "https://earthquake.usgs.gov/earthquakes/eventpage/ci41147856",
        "detail": "https://earthquake.usgs.gov/earthquakes/feed/v1.0/detail/ci41147856.geojson",
        "title": "M 2.6 - 10 km WNW of Corona, CA"
      },
      "geometry": {
        "type": "Point",
        "coordinates": [
          -117.665,
          33.9,
          5.12
        ]
      }
    },
    {
      "type": "Feature",
      "properties": {
        "mag": 1.16,
        "place": "3 km SE of The Geysers, CA",
        "time": 1746714837310,
        "updated": 1746715939486,
        "url": "https://earthquake.usgs.gov/earthquakes/eventpage/nc75178461",
        "detail": "https://earthquake.usgs.gov/earthquakes/feed/v1.0/detail/nc75178461.geojson",
        "title": "M 1.2 - 3 km SE of The Geysers, CA"
      },
      "geometry": {
        "type": "Point",
        "coordinates": [
          -122.731002807617,
          38.7576675415039,
          1.78999996185303
        ]
      }
    },
    {
      "type": "Feature",
      "properties": {
        "mag": 0.89,
        "place": "9 km SSE of Idyllwild, CA",
        "time": 1746714721430,
        "updated": 1746715664740,
        "url": "https://earthquake.usgs.gov/earthquakes/eventpage/ci41147840",
        "detail": "https://earthquake.usgs.gov/earthquakes/feed/v1.0/detail/ci41147840.geojson",
        "title": "M 0.9 - 9 km SSE of Idyllwild, CA"
      },
      "geometry": {
        "type": "Point",
        "coordinates": [
          -116.6853333,
          33.6661667,
          16.02
        ]
      }
    },
    {
      "type": "Feature",
      "properties": {
        "mag": 1.4,
        "place": "9 km NW of Happy Valley, Alaska",
        "time": 1746713426833,
        "updated": 1746714058044,
        "url": "https://earthquake.usgs.gov/earthquakes/eventpage/ak0255vx6owr",
        "detail": "https://earthquake.usgs.gov/earthquakes/feed/v1.0/detail/ak0255vx6owr.geojson",
        "title": "M 1.4 - 9 km NW of Happy Valley, Alaska"
      },
      "geometry": {
        "type": "Point",
        "coordinates": [
          -151.8649,
          60.0039,
          58.4
        ]
      }
    },
    {
      "type": "Feature",
      "properties": {
        "mag": 1.1,
        "place": "6 km NNW of The Geysers, CA",
        "time": 1746713195530,
        "updated": 1746714436331,
        "url": "https://earthquake.usgs.gov/earthquakes/eventpage/nc75178446",
        "detail": "https://earthquake.usgs.gov/earthquakes/feed/v1.0/detail/nc75178446.geojson",
        "title": "M 1.1 - 6 km NNW of The Geysers, CA"
      },
      "geometry": {
        "type": "Point",
        "coordinates": [
          -122.795669555664,
          38.8178329467773,
          2.29999995231628
        ]
      }
    }
  ]
}