{
  "type": "FeatureCollection",
  "metadata": {
    "generated": 1747742670000,
    "url": "https://earthquake.usgs.gov/earthquakes/feed/v1.0/summary/all_hour.geojson",
    "title": "USGS All Earthquakes, Past Hour",
    "status": 200,
    "api": "1.14.1",
    "count": 6
  },
  "features": [
    {
      "type": "Feature",
      "properties": {
        "mag": 1.65,
        "place": "9 km ENE of Calexico, CA",
        "time": 1747741115090,
        "updated": 1747741333482,
        "url": "https://earthquake.usgs.gov/earthquakes/eventpage/ci41157168",
        "detail": "https://earthquake.usgs.gov/earthquakes/feed/v1.0/detail/ci41157168.geojson",
        "title": "M 1.7 - 9 km ENE of Calexico, CA"
      },
      "geometry": {
        "type": "Point",
        "coordinates": [
          -115.4163333,
          32.725,
          15.32
        ]
      }
    },
    {
      "type": "Feature",
      "properties": {
        "mag": 1.47,
        "place": "8 km ENE of Calexico, CA",
        "time": 1747740597930,
        "updated": 1747740815411,
        "url": "https://earthquake.usgs.gov/earthquakes/eventpage/ci41157160",
        "detail": "https://earthquake.usgs.gov/earthquakes/feed/v1.0/detail/ci41157160.geojson",
        "title": "M 1.5 - 8 km ENE of Calexico, CA"
      },
      "geometry": {
        "type": "Point",
        "coordinates": [
          -115.423,
          32.7175,
          15.4
        ]
      }
    },
    {
      "type": "Feature",
      "properties": {
        "mag": 1.1,
        "place": "38 km NE of Beatty, Nevada",
        "time": 1747740452824,
        "updated": 1747740555818,
        "url": "https://earthquake.usgs.gov/earthquakes/eventpage/nn00897791",
        "detail": "https://earthquake.usgs.gov/earthquakes/feed/v1.0/detail/nn00897791.geojson",
        "title": "M 1.1 - 38 km NE of Beatty, Nevada"
      },
      "geometry": {
        "type": "Point",
        "coordinates": [
          -116.5075,
          37.1946,
          0
        ]
      }
    },
    {
      "type": "Feature",
      "properties": {
        "mag": 0.79,
        "place": "7 km E of Ridgecrest, CA",
        "time": 1747740066200,
        "updated": 1747740269353,
        "url": "https://earthquake.usgs.gov/earthquakes/eventpage/ci41157152",
        "detail": "https://earthquake.usgs.gov/earthquakes/feed/v1.0/detail/ci41157152.geojson",
        "title": "M 0.8 - 7 km E of Ridgecrest, CA"
      },
      "geometry": {
        "type": "Point",
        "coordinates": [
          -117.5953333,
          35.616,
          8.92
        ]
      }
    },
    {
      "type": "Feature",
      "properties": {
        "mag": 1.14,
        "place": "12 km WNW of Calipatria, CA",
        "time": 1747739790160,
        "updated": 1747739993269,
        "url": "https://earthquake.usgs.gov/earthquakes/eventpage/ci41157144",
        "detail": "https://earthquake.usgs.gov/earthquakes/feed/v1.0/detail/ci41157144.geojson",
        "title": "M 1.1 - 12 km WNW of Calipatria, CA"
      },
      "geometry": {
        "type": "Point",
        "coordinates": [
          -115.628,
          33.1775,
          3.39
        ]
      }
    },
    {
      "type": "Feature",
      "properties": {
        "mag": 1.61,
        "place": "7 km NE of Millville, CA",
        "time": 1747739399000,
        "updated": 1747741643761,
        "url": "https://earthquake.usgs.gov/earthquakes/eventpage/nc75184061",
        "detail": "https://earthquake.usgs.gov/earthquakes/feed/v1.0/detail/nc75184061.geojson",
        "title": "M 1.6 - 7 km NE of Millville, CA"
      },
      "geometry": {
        "type": "Point",
        "coordinates": [
          -122.144332885742,
          40.6105003356934,
          9.39000034332275
        ]
      }
    }
  ]
}