{
  "type": "FeatureCollection",
  "metadata": {
    "generated": 1746684178000,
    "url": "https://earthquake.usgs.gov/earthquakes/feed/v1.0/summary/all_hour.geojson",
    "title": "USGS All Earthquakes, Past Hour",
    "status": 200,
    "api": "1.14.1",
    "count": 7
  },
  "features": [
    {
      "type": "Feature",
      "properties": {
        "mag": 2.45,
        "place": "5 km SSE of Bajandas, Puerto Rico",
        "time": 1746682799020,
        "updated": 1746684065640,
        "url": "https://earthquake.usgs.gov/earthquakes/eventpage/pr71481663",
        "detail": "https://earthquake.usgs.gov/earthquakes/feed/v1.0/detail/pr71481663.geojson",
        "title": "M 2.5 - 5 km SSE of Bajandas, Puerto Rico"
      },
      "geometry": {
        "type": "Point",
        "coordinates": [
          -65.7578333333333,
          18.1095,
          10.25
        ]
      }
    },
    {
      "type": "Feature",
      "properties": {
        "mag": 0.8,
        "place": "8 km NNW of The Geysers, CA",
        "time": 1746681993300,
        "updated": 1746682091269,
        "url": "https://earthquake.usgs.gov/earthquakes/eventpage/nc75178236",
        "detail": "https://earthquake.usgs.gov/earthquakes/feed/v1.0/detail/nc75178236.geojson",
        "title": "M 0.8 - 8 km NNW of The Geysers, CA"
      },
      "geometry": {
        "type": "Point",
        "coordinates": [
          -122.815330505371,
          38.828498840332,
          1.88999998569489
        ]
      }
    },
    {
      "type": "Feature",
      "properties": {
        "mag": 4.5,
        "place": "57 km W of Bardaskan, Iran",
        "time": 1746681788807,
        "updated": 1746683276040,
        "url": "https://earthquake.usgs.gov/earthquakes/eventpage/us7000pxvp",
        "detail": "https://earthquake.usgs.gov/earthquakes/feed/v1.0/detail/us7000pxvp.geojson",
        "title": "M 4.5 - 57 km W of Bardaskan, Iran"
      },
      "geometry": {
        "type": "Point",
        "coordinates": [
          57.3364,
          35.3089,
          10
        ]
      }
    },
    {
      "type": "Feature",
      "properties": {
        "mag": 0.27,
        "place": "6 km WNW of Cobb, CA",
        "time": 1746681696680,
        "updated": 1746682639919,
        "url": "https://earthquake.usgs.gov/earthquakes/eventpage/nc75178226",
        "detail": "https://earthquake.usgs.gov/earthquakes/feed/v1.0/detail/nc75178226.geojson",
        "title": "M 0.3 - 6 km WNW of Cobb, CA"
      },
      "geometry": {
        "type": "Point",
        "coordinates": [
          -122.792335510254,
          38.8334999084473,
          1.74000000953674
        ]
      }
    },
    {
      "type": "Feature",
      "properties": {
        "mag": 0.93,
        "place": "18 km ESE of Anza, CA",
        "time": 1746680967680,
        "updated": 1746681180359,
        "url": "https://earthquake.usgs.gov/earthquakes/eventpage/ci41147480",
        "detail": "https://earthquake.usgs.gov/earthquakes/feed/v1.0/detail/ci41147480.geojson",
        "title": "M 0.9 - 18 km ESE of Anza, CA"
      },
      "geometry": {
        "type": "Point",
        "coordinates": [
          -116.5081667,
          33.4783333,
          12.56
        ]
      }
    },
    {
      "type": "Feature",
      "properties": {
        "mag": 1.4,
        "place": "15 km NNW of Cooper Landing, Alaska",
        "time": 1746680906609,
        "updated": 1746681053656,
        "url": "https://earthquake.usgs.gov/earthquakes/eventpage/ak0255vrtd0k",
        "detail": "https://earthquake.usgs.gov/earthquakes/feed/v1.0/detail/ak0255vrtd0k.geojson",
        "title": "M 1.4 - 15 km NNW of Cooper Landing, Alaska"
      },
      "geometry": {
        "type": "Point",
        "coordinates": [
          -149.9728,
          60.6088,
          32
        ]
      }
    },
    {
      "type": "Feature",
      "properties": {
        "mag": 1.07,
        "place": "9 km NW of The Geysers, CA",
        "time": 1746680769900,
        "updated": 1746680866065,
        "url": "https://earthquake.usgs.gov/earthquakes/eventpage/nc75178221",
        "detail": "https://earthquake.usgs.gov/earthquakes/feed/v1.0/detail/nc75178221.geojson",
        "title": "M 1.1 - 9 km NW of The Geysers, CA"
      },
      "geometry": {
        "type": "Point",
        "coordinates": [
          -122.842163085938,
          38.8224983215332,
          1.78999996185303
        ]
      }
    }
  ]
}