{
  "type": "FeatureCollection",
  "metadata": {
    "generated": 1747746690000,
    "url": "https://earthquake.usgs.gov/earthquakes/feed/v1.0/summary/all_hour.geojson",
    "title": "USGS All Earthquakes, Past Hour",
    "status": 200,
    "api": "1.14.1",
    "count": 10
  },
  "features": [
    {
      "type": "Feature",
      "properties": {
        "mag": 1.03,
        "place": "9 km ENE of Julian, CA",
        "time": 1747746298590,
        "updated": 1747746508290,
        "url": "https://earthquake.usgs.gov/earthquakes/eventpage/ci41157216",
        "detail": "https://earthquake.usgs.gov/earthquakes/feed/v1.0/detail/ci41157216.geojson",
        "title": "M 1.0 - 9 km ENE of Julian, CA"
      },
      "geometry": {
        "type": "Point",
        "coordinates": [
          -116.52,
          33.1181667,
          13.22
        ]
      }
    },
    {
      "type": "Feature",
      "properties": {
        "mag": 0.59,
        "place": "4 km NNW of The Geysers, CA",
        "time": 1747746163910,
        "updated": 1747746260993,
        "url": "https://earthquake.usgs.gov/earthquakes/eventpage/nc75184086",
        "detail": "https://earthquake.usgs.gov/earthquakes/feed/v1.0/detail/nc75184086.geojson",
        "title": "M 0.6 - 4 km NNW of The Geysers, CA"
      },
      "geometry": {
        "type": "Point",
        "coordinates": [
          -122.78150177002,
          38.8071670532227,
          3.5699999332428
        ]
      }
    },
    {
      "type": "Feature",
      "properties": {
        "mag": 0.77,
        "place": "10 km NW of The Geysers, CA",
        "time": 1747746082160,
        "updated": 1747746181174,
        "url": "https://earthquake.usgs.gov/earthquakes/eventpage/nc75184081",
        "detail": "https://earthquake.usgs.gov/earthquakes/feed/v1.0/detail/nc75184081.geojson",
        "title": "M 0.8 - 10 km NW of The Geysers, CA"
      },
      "geometry": {
        "type": "Point",
        "coordinates": [
          -122.85383605957,
          38.8216667175293,
          2.50999999046326
        ]
      }
    },
    {
      "type": "Feature",
      "properties": {
        "mag": 1.46,
        "place": "6 km NW of The Geysers, CA",
        "time": 1747746009250,
        "updated": 1747746205490,
        "url": "https://earthquake.usgs.gov/earthquakes/eventpage/nc75184076",
        "detail": "https://earthquake.usgs.gov/earthquakes/feed/v1.0/detail/nc75184076.geojson",
        "title": "M 1.5 - 6 km NW of The Geysers, CA"
      },
      "geometry": {
        "type": "Point",
        "coordinates": [
          -122.815170288086,
          38.8009986877441,
          2.64000010490417
        ]
      }
    },
    {
      "type": "Feature",
      "properties": {
        "mag": 1.2,
        "place": "10 km SSE of Salton City, CA",
        "time": 1747745994610,
        "updated": 1747746211985,
        "url": "https://earthquake.usgs.gov/earthquakes/eventpage/ci41157208",
        "detail": "https://earthquake.usgs.gov/earthquakes/feed/v1.0/detail/ci41157208.geojson",
        "title": "M 1.2 - 10 km SSE of Salton City, CA"
      },
      "geometry": {
        "type": "Point",
        "coordinates": [
          -115.9331667,
          33.2141667,
          7.81
        ]
      }
    },
    {
      "type": "Feature",
      "properties": {
        "mag": 1.8,
        "place": "22 km ENE of Chase, Alaska",
        "time": 1747745924117,
        "updated": 1747746067814,
        "url": "https://earthquake.usgs.gov/earthquakes/eventpage/ak0256fqqbbv",
        "detail": "https://earthquake.usgs.gov/earthquakes/feed/v1.0/detail/ak0256fqqbbv.geojson",
        "title": "M 1.8 - 22 km ENE of Chase, Alaska"
      },
      "geometry": {
        "type": "Point",
        "coordinates": [
          -149.6764,
          62.499,
          11.9
        ]
      }
    },
    {
      "type": "Feature",
      "properties": {
        "mag": 0.22,
        "place": "9 km WNW of Cobb, CA",
        "time": 1747745686730,
        "updated": 1747745781323,
        "url": "https://earthquake.usgs.gov/earthquakes/eventpage/nc75184071",
        "detail": "https://earthquake.usgs.gov/earthquakes/feed/v1.0/detail/nc75184071.geojson",
        "title": "M 0.2 - 9 km WNW of Cobb, CA"
      },
      "geometry": {
        "type": "Point",
        "coordinates": [
          -122.818336486816,
          38.848331451416,
          0.589999973773956
        ]
      }
    },
    {
      "type": "Feature",
      "properties": {
        "mag": 0.73,
        "place": "17 km NE of Coachella, CA",
        "time": 1747745637400,
        "updated": 1747745920959,
        "url": "https://earthquake.usgs.gov/earthquakes/eventpage/ci41157200",
        "detail": "https://earthquake.usgs.gov/earthquakes/feed/v1.0/detail/ci41157200.geojson",
        "title": "M 0.7 - 17 km NE of Coachella, CA"
      },
      "geometry": {
        "type": "Point",
        "coordinates": [
          -116.0516667,
          33.7988333,
          9.65
        ]
      }
    },
    {
      "type": "Feature",
      "properties": {
        "mag": 1.11,
        "place": "4 km ENE of Cabazon, CA",
        "time": 1747743488120,
        "updated": 1747743721108,
        "url": "https://earthquake.usgs.gov/earthquakes/eventpage/ci41157192",
        "detail": "https://earthquake.usgs.gov/earthquakes/feed/v1.0/detail/ci41157192.geojson",
        "title": "M 1.1 - 4 km ENE of Cabazon, CA"
      },
      "geometry": {
        "type": "Point",
        "coordinates": [
          -116.7446667,
          33.9358333,
          12.68
        ]
      }
    },
    {
      "type": "Feature",
      "properties": {
        "mag": 0.71,
        "place": "9 km WNW of Cobb, CA",
        "time": 1747743388800,
        "updated": 1747745838253,
        "url": "https://earthquake.usgs.gov/earthquakes/eventpage/nc75184066",
        "detail": "https://earthquake.usgs.gov/earthquakes/feed/v1.0/detail/nc75184066.geojson",
        "title": "M 0.7 - 9 km WNW of Cobb, CA"
      },
      "geometry": {
        "type": "Point",
        "coordinates": [
          -122.817832946777,
          38.8486671447754,
          0.340000003576279
        ]
      }
    }
  ]
}