{
  "type": "FeatureCollection",
  "metadata": {
    "generated": 1747411344000,
    "url": "https://earthquake.usgs.gov/earthquakes/feed/v1.0/summary/all_hour.geojson",
    "title": "USGS All Earthquakes, Past Hour",
    "status": 200,
    "api": "1.14.1",
    "count": 7
  },
  "features": [
    {
      "type": "Feature",
      "properties": {
        "mag": 0.7,
        "place": "42 km WNW of Beatty, Nevada",
        "time": 1747410653811,
        "updated": 1747410785011,
        "url": "https://earthquake.usgs.gov/earthquakes/eventpage/nn00897693",
        "detail": "https://earthquake.usgs.gov/earthquakes/feed/v1.0/detail/nn00897693.geojson",
        "title": "M 0.7 - 42 km WNW of Beatty, Nevada"
      },
      "geometry": {
        "type": "Point",
        "coordinates": [
          -117.1638,
          37.1106,
          0
        ]
      }
    },
    {
      "type": "Feature",
      "properties": {
        "mag": 0.76,
        "place": "5 km WNW of Cobb, CA",
        "time": 1747410615940,
        "updated": 1747410712536,
        "url": "https://earthquake.usgs.gov/earthquakes/eventpage/nc75182917",
        "detail": "https://earthquake.usgs.gov/earthquakes/feed/v1.0/detail/nc75182917.geojson",
        "title": "M 0.8 - 5 km WNW of Cobb, CA"
      },
      "geometry": {
        "type": "Point",
        "coordinates": [
          -122.784332275391,
          38.826831817627,
          1.70000004768372
        ]
      }
    },
    {
      "type": "Feature",
      "properties": {
        "mag": 2.4,
        "place": "36 km SSW of Kokhanok, Alaska",
        "time": 1747410185471,
        "updated": 1747410406241,
        "url": "https://earthquake.usgs.gov/earthquakes/eventpage/ak0256969xmi",
        "detail": "https://earthquake.usgs.gov/earthquakes/feed/v1.0/detail/ak0256969xmi.geojson",
        "title": "M 2.4 - 36 km SSW of Kokhanok, Alaska"
      },
      "geometry": {
        "type": "Point",
        "coordinates": [
          -154.9206,
          59.1227,
          174.5
        ]
      }
    },
    {
      "type": "Feature",
      "properties": {
        "mag": 0.84,
        "place": "13 km NW of Ocotillo Wells, CA",
        "time": 1747409904430,
        "updated": 1747410111531,
        "url": "https://earthquake.usgs.gov/earthquakes/eventpage/ci41154296",
        "detail": "https://earthquake.usgs.gov/earthquakes/feed/v1.0/detail/ci41154296.geojson",
        "title": "M 0.8 - 13 km NW of Ocotillo Wells, CA"
      },
      "geometry": {
        "type": "Point",
        "coordinates": [
          -116.2188333,
          33.2353333,
          6.69
        ]
      }
    },
    {
      "type": "Feature",
      "properties": {
        "mag": 1.6,
        "place": "59 km WNW of Petersville, Alaska",
        "time": 1747409896746,
        "updated": 1747410013642,
        "url": "https://earthquake.usgs.gov/earthquakes/eventpage/ak0256968vqi",
        "detail": "https://earthquake.usgs.gov/earthquakes/feed/v1.0/detail/ak0256968vqi.geojson",
        "title": "M 1.6 - 59 km WNW of Petersville, Alaska"
      },
      "geometry": {
        "type": "Point",
        "coordinates": [
          -151.8409,
          62.7065,
          8.7
        ]
      }
    },
    {
      "type": "Feature",
      "properties": {
        "mag": 0.55,
        "place": "7 km WNW of Cobb, CA",
        "time": 1747408791450,
        "updated": 1747410735958,
        "url": "https://earthquake.usgs.gov/earthquakes/eventpage/nc75182907",
        "detail": "https://earthquake.usgs.gov/earthquakes/feed/v1.0/detail/nc75182907.geojson",
        "title": "M 0.6 - 7 km WNW of Cobb, CA"
      },
      "geometry": {
        "type": "Point",
        "coordinates": [
          -122.806663513184,
          38.835334777832,
          2.3199999332428
        ]
      }
    },
    {
      "type": "Feature",
      "properties": {
        "mag": 1.08,
        "place": "7 km NNW of The Geysers, CA",
        "time": 1747407861730,
        "updated": 1747409236788,
        "url": "https://earthquake.usgs.gov/earthquakes/eventpage/nc75182897",
        "detail": "https://earthquake.usgs.gov/earthquakes/feed/v1.0/detail/nc75182897.geojson",
        "title": "M 1.1 - 7 km NNW of The Geysers, CA"
      },
      "geometry": {
        "type": "Point",
        "coordinates": [
          -122.802833557129,
          38.8258323669434,
          3.0699999332428
        ]
      }
    }
  ]
}