{
  "type": "FeatureCollection",
  "metadata": {
    "generated": 1746972144000,
    "url": "https://earthquake.usgs.gov/earthquakes/feed/v1.0/summary/all_hour.geojson",
    "title": "USGS All Earthquakes, Past Hour",
    "status": 200,
    "api": "1.14.1",
    "count": 8
  },
  "features": [
    {
      "type": "Feature",
      "properties": {
        "mag": 1.21,
        "place": "13 km SE of Ocotillo, CA",
        "time": 1746971896090,
        "updated": 1746972106294,
        "url": "https://earthquake.usgs.gov/earthquakes/eventpage/ci41150856",
        "detail": "https://earthquake.usgs.gov/earthquakes/feed/v1.0/detail/ci41150856.geojson",
        "title": "M 1.2 - 13 km SE of Ocotillo, CA"
      },
      "geometry": {
        "type": "Point",
        "coordinates": [
          -115.891,
          32.6531667,
          7.65
        ]
      }
    },
    {
      "type": "Feature",
      "properties": {
        "mag": 0.9,
        "place": "16 km ESE of Livengood, Alaska",
        "time": 1746971558129,
        "updated": 1746971687760,
        "url": "https://earthquake.usgs.gov/earthquakes/eventpage/ak02560vgbqc",
        "detail": "https://earthquake.usgs.gov/earthquakes/feed/v1.0/detail/ak02560vgbqc.geojson",
        "title": "M 0.9 - 16 km ESE of Livengood, Alaska"
      },
      "geometry": {
        "type": "Point",
        "coordinates": [
          -148.2485,
          65.4472,
          11.4
        ]
      }
    },
    {
      "type": "Feature",
      "properties": {
        "mag": 1.06,
        "place": "15 km SSW of Searles Valley, CA",
        "time": 1746971415780,
        "updated": 1746971620090,
        "url": "https://earthquake.usgs.gov/earthquakes/eventpage/ci41150848",
        "detail": "https://earthquake.usgs.gov/earthquakes/feed/v1.0/detail/ci41150848.geojson",
        "title": "M 1.1 - 15 km SSW of Searles Valley, CA"
      },
      "geometry": {
        "type": "Point",
        "coordinates": [
          -117.456,
          35.638,
          6.73
        ]
      }
    },
    {
      "type": "Feature",
      "properties": {
        "mag": 0.77,
        "place": "7 km NNW of The Geysers, CA",
        "time": 1746970782390,
        "updated": 1746970877286,
        "url": "https://earthquake.usgs.gov/earthquakes/eventpage/nc75179811",
        "detail": "https://earthquake.usgs.gov/earthquakes/feed/v1.0/detail/nc75179811.geojson",
        "title": "M 0.8 - 7 km NNW of The Geysers, CA"
      },
      "geometry": {
        "type": "Point",
        "coordinates": [
          -122.810501098633,
          38.8219985961914,
          2.70000004768372
        ]
      }
    },
    {
      "type": "Feature",
      "properties": {
        "mag": 2.1,
        "place": "34 km NW of Toyah, Texas",
        "time": 1746970573090,
        "updated": 1746971317375,
        "url": "https://earthquake.usgs.gov/earthquakes/eventpage/tx2025jeoq",
        "detail": "https://earthquake.usgs.gov/earthquakes/feed/v1.0/detail/tx2025jeoq.geojson",
        "title": "M 2.1 - 34 km NW of Toyah, Texas"
      },
      "geometry": {
        "type": "Point",
        "coordinates": [
          -104.022,
          31.562,
          4.9798
        ]
      }
    },
    {
      "type": "Feature",
      "properties": {
        "mag": 1.32,
        "place": "7 km NW of The Geysers, CA",
        "time": 1746970431530,
        "updated": 1746971538754,
        "url": "https://earthquake.usgs.gov/earthquakes/eventpage/nc75179806",
        "detail": "https://earthquake.usgs.gov/earthquakes/feed/v1.0/detail/nc75179806.geojson",
        "title": "M 1.3 - 7 km NW of The Geysers, CA"
      },
      "geometry": {
        "type": "Point",
        "coordinates": [
          -122.823829650879,
          38.8186683654785,
          2.00999999046326
        ]
      }
    },
    {
      "type": "Feature",
      "properties": {
        "mag": 1.6,
        "place": "29 km NW of Toyah, Texas",
        "time": 1746969928443,
        "updated": 1746970650296,
        "url": "https://earthquake.usgs.gov/earthquakes/eventpage/tx2025jeog",
        "detail": "https://earthquake.usgs.gov/earthquakes/feed/v1.0/detail/tx2025jeog.geojson",
        "title": "M 1.6 - 29 km NW of Toyah, Texas"
      },
      "geometry": {
        "type": "Point",
        "coordinates": [
          -103.989,
          31.518,
          5.4733
        ]
      }
    },
    {
      "type": "Feature",
      "properties": {
        "mag": 2.9,
        "place": "37 km WSW of Skwentna, Alaska",
        "time": 1746969808585,
        "updated": 1746971403040,
        "url": "https://earthquake.usgs.gov/earthquakes/eventpage/ak02560va389",
        "detail": "https://earthquake.usgs.gov/earthquakes/feed/v1.0/detail/ak02560va389.geojson",
        "title": "M 2.9 - 37 km WSW of Skwentna, Alaska"
      },
      "geometry": {
        "type": "Point",
        "coordinates": [
          -152.0629,
          61.8729,
          4.9
        ]
      }
    }
  ]
}